argshell/__init__.py
argshell/argshell.py
argshell/py.typed
argshell-1.6.6.dist-info/METADATA
argshell-1.6.6.dist-info/WHEEL
argshell-1.6.6.dist-info/licenses/LICENSE.txt
argshell-1.6.6.dist-info/RECORD
